ontouml_models_lib/__init__.py
ontouml_models_lib/catalog.py
ontouml_models_lib/enumerations.py
ontouml_models_lib/model.py
ontouml_models_lib/py.typed
ontouml_models_lib/query.py
ontouml_models_lib/utils/__init__.py
ontouml_models_lib/utils/queryable_element.py
ontouml_models_lib-1.0.0b4.dist-info/LICENSE
ontouml_models_lib-1.0.0b4.dist-info/METADATA
ontouml_models_lib-1.0.0b4.dist-info/WHEEL
ontouml_models_lib-1.0.0b4.dist-info/RECORD
