Metadata-Version: 2.1
Name: ontouml-models-lib
Version: 1.0.0b4
Summary: ontouml-models-lib Python Library
Home-page: https://w3id.org/ontouml/models-lib
License: Apache-2.0
Keywords: ontouml,ontouml-models,catalog,ontology,ontology-engineering,python,sparql
Author: Pedro Paulo F. Barcelos
Author-email: p.p.favatobarcelos@utwente.nl
Requires-Python: >=3.09,<4.0
Classifier: License :: OSI Approved :: Apache Software License
Classifier: Programming Language :: Python :: 3
Classifier: Programming Language :: Python :: 3.9
Classifier: Programming Language :: Python :: 3.10
Classifier: Programming Language :: Python :: 3.11
Classifier: Programming Language :: Python :: 3.12
Requires-Dist: loguru (>=0.7.2,<0.8.0)
Requires-Dist: pandas (>=2.2.2,<3.0.0)
Requires-Dist: pyyaml (>=6.0.2,<7.0.0)
Requires-Dist: rdflib (>=7.0.0,<8.0.0)
Project-URL: Documentation, https://w3id.org/ontouml/models-lib/docs
Project-URL: PyPi Project, https://pypi.org/project/ontouml-models-lib/
Project-URL: Repository, https://w3id.org/ontouml/models-lib
